.gitattributes
.gitignore
LICENSE
MANIFEST.in
README.md
pyproject.toml
examples/argument_parser/1_simple.py
examples/cursor/1_move.py
examples/cursor/2_save_cursor.py
examples/forms/1_form.py
examples/menus/1_Simple.py
examples/menus/2_Options.py
examples/menus/3_Dynamic.py
examples/menus/4_Structural.py
ultra_cli/__init__.py
ultra_cli/cursor.py
ultra_cli.egg-info/PKG-INFO
ultra_cli.egg-info/SOURCES.txt
ultra_cli.egg-info/dependency_links.txt
ultra_cli.egg-info/requires.txt
ultra_cli.egg-info/top_level.txt
ultra_cli/argument_parser/__init__.py
ultra_cli/argument_parser/complex_handlers.py
ultra_cli/argument_parser/exceptions.py
ultra_cli/argument_parser/parser.py
ultra_cli/argument_parser/utils.py
ultra_cli/forms/__init__.py
ultra_cli/forms/form.py
ultra_cli/forms/question.py
ultra_cli/forms/validation.py
ultra_cli/menus/__init__.py
ultra_cli/menus/base.py
ultra_cli/menus/menu.py
ultra_cli/menus/option.py
ultra_cli/menus/structual_menu.py
ultra_cli/styles/__init__.py
ultra_cli/styles/attributes.py
ultra_cli/styles/colors.py
ultra_cli/styles/out.py
ultra_cli/utils/__init__.py