Metadata-Version: 2.1
Name: ultra-cli
Version: 0.6.0
Summary: CLI app creation made easier
Author-email: Ramin-RX7 <rawmin.rx@gmail.com>
License: LGPL
Project-URL: Homepage, https://github.com/Ramin-RX7/Ultra-CLI
Project-URL: Bug Tracker, https://github.com/Ramin-RX7/Ultra-CLI/issues
Project-URL: documentation, https://github.com/Ramin-RX7/Ultra-CLI/#Ultra-CLI
Classifier: Programming Language :: Python :: 3
Requires-Python: >=3.10
License-File: LICENSE
Requires-Dist: pydantic
